fastapi_spammer_protection/__init__.py
fastapi_spammer_protection/matcher.py
fastapi_spammer_protection/middleware.py
fastapi_spammer_protection/url.py
fastapi_spammer_protection/vulnerable_urls.py
fastapi_spammer_protection-1.2.0.dist-info/LICENSE
fastapi_spammer_protection-1.2.0.dist-info/WHEEL
fastapi_spammer_protection-1.2.0.dist-info/METADATA
fastapi_spammer_protection-1.2.0.dist-info/RECORD
